let/__about__.py
let/__init__.py
let/_let.py
let/py.typed
let3-2.1.1.dist-info/licenses/LICENSE
let3-2.1.1.dist-info/METADATA
let3-2.1.1.dist-info/WHEEL
let3-2.1.1.dist-info/top_level.txt
let3-2.1.1.dist-info/zip-safe
let3-2.1.1.dist-info/RECORD
