Metadata-Version: 2.4
Name: let3
Version: 2.1.1
Summary: Assign variables wherever, whenever you want.
Author-email: Adam Karpierz <adam@karpierz.net>, Taylor Marks <taylor@marksfam.com>
Maintainer-email: Adam Karpierz <adam@karpierz.net>
License-Expression: MIT
Project-URL: Homepage, https://pypi.org/project/let3/
Project-URL: Documentation, https://karpierz.github.io/let3/
Project-URL: History, https://karpierz.github.io/let3/CHANGES.html
Project-URL: Download, https://pypi.org/project/let3/
Project-URL: Repository, https://github.com/karpierz/let3
Project-URL: Tracker, https://github.com/karpierz/let3/issues
Project-URL: Sponsoring, https://www.paypal.com/donate/?hosted_button_id=FX8L7CJUGLW7S
Keywords: let,let3,assign,assignment,var,variable,conditional,if,while
Platform: any
Classifier: Development Status :: 5 - Production/Stable
Classifier: Intended Audience :: Developers
Classifier: Operating System :: OS Independent
Classifier: Natural Language :: Polish
Classifier: Programming Language :: Python
Classifier: Programming Language :: Python :: 3
Classifier: Programming Language :: Python :: 3.10
Classifier: Programming Language :: Python :: 3.11
Classifier: Programming Language :: Python :: 3.12
Classifier: Programming Language :: Python :: 3.13
Classifier: Programming Language :: Python :: 3.14
Classifier: Programming Language :: Python :: 3 :: Only
Classifier: Programming Language :: Python :: Implementation :: CPython
Classifier: Programming Language :: Python :: Implementation :: PyPy
Classifier: Topic :: Software Development :: Libraries :: Python Modules
Classifier: Typing :: Typed
Requires-Python: <4.0.0,>=3.10.0
License-File: LICENSE
Requires-Dist: typing-extensions>=4.15.0
Requires-Dist: pkg-about>=2.1.0
Dynamic: license-file
